evolutionary_policy_optimization/__init__.py
evolutionary_policy_optimization/distributed.py
evolutionary_policy_optimization/env_wrappers.py
evolutionary_policy_optimization/epo.py
evolutionary_policy_optimization/experimental.py
evolutionary_policy_optimization/mock_env.py
evolutionary_policy_optimization-0.2.15.dist-info/METADATA
evolutionary_policy_optimization-0.2.15.dist-info/WHEEL
evolutionary_policy_optimization-0.2.15.dist-info/licenses/LICENSE
evolutionary_policy_optimization-0.2.15.dist-info/RECORD
