Metadata-Version: 2.4
Name: evolutionary-policy-optimization
Version: 0.2.15
Summary: EPO - Pytorch
Project-URL: Homepage, https://pypi.org/project/evolutionary-policy-optimization/
Project-URL: Repository, https://github.com/lucidrains/evolutionary-policy-optimization
Author-email: Phil Wang <lucidrains@gmail.com>
License: MIT License
License-File: LICENSE
Keywords: artificial intelligence,deep learning,genetic algorithms,reinforcement learning,robotics
Classifier: Development Status :: 4 - Beta
Classifier: Intended Audience :: Developers
Classifier: License :: OSI Approved :: MIT License
Classifier: Programming Language :: Python :: 3.8
Classifier: Topic :: Scientific/Engineering :: Artificial Intelligence
Requires-Python: >=3.9
Requires-Dist: accelerate>=1.6.0
Requires-Dist: adam-atan2-pytorch
Requires-Dist: assoc-scan>=0.0.2
Requires-Dist: einops>=0.8.1
Requires-Dist: einx>=0.3.0
Requires-Dist: ema-pytorch>=0.7.7
Requires-Dist: hl-gauss-pytorch>=0.1.19
Requires-Dist: torch>=2.2
Requires-Dist: tqdm
Provides-Extra: examples
Requires-Dist: numpy; extra == 'examples'
Requires-Dist: pufferlib>=2.0.6; extra == 'examples'
Requires-Dist: tqdm; extra == 'examples'
Provides-Extra: experimental
Requires-Dist: tensordict; extra == 'experimental'
Requires-Dist: torchvision; extra == 'experimental'
Provides-Extra: test
Requires-Dist: pytest; extra == 'test'
Requires-Dist: ruff>=0.4.2; extra == 'test'
